[{"id":0,"url":"https://github.com/SilentNotaryEcosystem/UIPS/blob/main/uip-1.mediawiki","name":"uip-1.mediawiki","estimationHours":7,"ubxPrice":10500,"usdtPrice":"0.48","performer":{"nickname":"666","walletAddress":""},"deleted":false,"success":true},{"id":1,"url":"https://github.com/SilentNotaryEcosystem/UIPS/blob/main/uip-2.mediawiki","name":"uip-2.mediawiki","estimationHours":99,"ubxPrice":148500,"usdtPrice":"6.79","performer":{"nickname":"","walletAddress":""},"deleted":false,"success":true},{"id":2,"url":"https://github.com/SilentNotaryEcosystem/UIPS/blob/main/uip-3.mediawiki","name":"uip-3.mediawiki","estimationHours":0,"ubxPrice":0,"usdtPrice":"0.00","performer":{"nickname":"","walletAddress":""},"deleted":false,"success":true},{"id":3,"url":"https://github.com/SilentNotaryEcosystem/UIPS/blob/main/uip-4.mediawiki","name":"uip-4.mediawiki","estimationHours":0,"ubxPrice":0,"usdtPrice":"0.00","performer":{"nickname":"","walletAddress":""},"deleted":false,"success":true}]